toucan_client/__init__.py
toucan_client/client.py
toucan_client/py.typed
toucan_client-1.1.2.dist-info/WHEEL
toucan_client-1.1.2.dist-info/METADATA
toucan_client-1.1.2.dist-info/RECORD
