Metadata-Version: 2.1
Name: toucan-client
Version: 1.1.2
Summary: Toucan API client
Home-page: https://github.com/ToucanToco/toucan-client
License: BSD-3-Clause
Author: Toucan Toco
Author-email: dev@toucantoco.com
Requires-Python: >=3.8,<4.0
Classifier: Intended Audience :: Developers
Classifier: License :: OSI Approved :: BSD License
Classifier: Programming Language :: Python :: 3
Classifier: Programming Language :: Python :: 3 :: Only
Classifier: Programming Language :: Python :: 3.10
Classifier: Programming Language :: Python :: 3.8
Classifier: Programming Language :: Python :: 3.9
Classifier: Typing :: Typed
Requires-Dist: requests (>=2.23,<3.0)
Project-URL: Documentation, https://toucantoco.github.io/toucan-client
Project-URL: Repository, https://github.com/ToucanToco/toucan-client
